mkdirs
